djangoroku/__init__.py
djangoroku/djangoroku.py
djangoroku-0.1.2.dist-info/LICENSE.txt
djangoroku-0.1.2.dist-info/METADATA
djangoroku-0.1.2.dist-info/WHEEL
djangoroku-0.1.2.dist-info/top_level.txt
djangoroku-0.1.2.dist-info/RECORD
