Metadata-Version: 2.1
Name: djangoroku
Version: 0.1.2
Summary: A package that helps to deploy django application to heroku
Home-page: https://github.com/ioi2908/djangoroku
Author: Stanley Ruheza
Author-email: 2001stany@gmail.com
License: MIT
Download-URL: https://github.com/ioi2908/djangoroku/archive/v_01.tar.gz
Keywords: django,heroku,deploy django,django heroku
Platform: UNKNOWN
Classifier: Development Status :: 3 - Alpha
Classifier: Intended Audience :: Developers
Classifier: Topic :: Software Development :: Build Tools
Classifier: License :: OSI Approved :: MIT License
Classifier: Programming Language :: Python :: 3
Classifier: Programming Language :: Python :: 3.4
Classifier: Programming Language :: Python :: 3.5
Classifier: Programming Language :: Python :: 3.6
Classifier: Programming Language :: Python :: 3.8
Requires-Dist: coloredlogs
Requires-Dist: setuptools
Requires-Dist: wheel
